engarde/__init__.py
engarde/_version.py
engarde/checks.py
engarde/decorators.py
engarde/generic.py
engarde-0.4.0.dist-info/DESCRIPTION.rst
engarde-0.4.0.dist-info/METADATA
engarde-0.4.0.dist-info/RECORD
engarde-0.4.0.dist-info/WHEEL
engarde-0.4.0.dist-info/metadata.json
engarde-0.4.0.dist-info/top_level.txt
